nb_hdr_plotter/__init__.py
nb_hdr_plotter/hdr_manipulation.py
nb_hdr_plotter/hdr_tool.py
nb_hdr_plotter/histostats_quick_plotter.py
nb_hdr_plotter/output_handling.py
nb_hdr_plotter/tools.py
nb_hdr_plotter-0.1.2.dist-info/LICENSE.txt
nb_hdr_plotter-0.1.2.dist-info/METADATA
nb_hdr_plotter-0.1.2.dist-info/WHEEL
nb_hdr_plotter-0.1.2.dist-info/entry_points.txt
nb_hdr_plotter-0.1.2.dist-info/top_level.txt
nb_hdr_plotter-0.1.2.dist-info/RECORD
