Metadata-Version: 2.1
Name: nb-hdr-plotter
Version: 0.1.2
Summary: Tool to plot HDR histogram data and histostats data generated by NoSQLBench
Home-page: https://github.com/hemidactylus/nb_hdr_plotter
Author: Stefano Lottini
Author-email: stefano.lottini@datastax.com
License: LICENSE.txt
Keywords: nosqlbench,plotting,hdr
Classifier: Development Status :: 4 - Beta
Classifier: Environment :: Console
Classifier: Intended Audience :: Developers
Classifier: License :: OSI Approved :: Apache Software License
Classifier: Programming Language :: Python :: 3
Classifier: Programming Language :: Python :: 3.8
Classifier: Programming Language :: Python :: 3.9
Classifier: Programming Language :: Python :: 3.10
Classifier: Programming Language :: Python :: 3 :: Only
Requires-Python: >=3.8, <4
License-File: LICENSE.txt
Requires-Dist: hdrhistogram (>=0.9.1)
Requires-Dist: matplotlib (<4,>=3.0.0)
